onnx_extended-0.4.0.dist-info/RECORD
onnx_extended-0.4.0.dist-info/WHEEL
onnx_extended-0.4.0.dist-info/top_level.txt
onnx_extended-0.4.0.dist-info/LICENSE.txt
onnx_extended-0.4.0.dist-info/METADATA
onnx_extended/memory_peak.py
onnx_extended/_common.py
onnx_extended/__init__.py
onnx_extended/_command_lines_parser.py
onnx_extended/ext_test_case.py
onnx_extended/_command_lines.py
onnx_extended/args.py
onnx_extended/_config.py
onnx_extended/__main__.py
onnx_extended/tools/js_profile.py
onnx_extended/tools/ort_debug.py
onnx_extended/tools/stats_nodes.py
onnx_extended/tools/__init__.py
onnx_extended/tools/onnx_nodes.py
onnx_extended/tools/run_onnx.py
onnx_extended/tools/run_onnx_main.py
onnx_extended/tools/onnx_inline.py
onnx_extended/tools/onnx_io.py
onnx_extended/tools/graph/onnx_graph_transformer.py
onnx_extended/tools/graph/onnx_custom_ops.py
onnx_extended/tools/graph/__init__.py
onnx_extended/tools/graph/onnx_graph_struct.py
onnx_extended/tools/graph/errors.py
onnx_extended/tools/einsum/einsum_fct.py
onnx_extended/tools/einsum/blas_lapack.py
onnx_extended/tools/einsum/einsum_config.py
onnx_extended/tools/einsum/__init__.py
onnx_extended/tools/einsum/einsum_bench.py
onnx_extended/tools/einsum/einsum_ml.py
onnx_extended/tools/einsum/einsum_impl_classes.py
onnx_extended/tools/einsum/einsum_impl_ext.py
onnx_extended/tools/einsum/einsum_impl.py
onnx_extended/.dylibs/libomp.dylib
onnx_extended/.dylibs/libonnxruntime.1.19.2.dylib
onnx_extended/plotting/benchmark.py
onnx_extended/plotting/__init__.py
onnx_extended/plotting/data.py
onnx_extended/ortcy/__init__.py
onnx_extended/ortcy/wrap/ortinf.cpp
onnx_extended/ortcy/wrap/ortapi.cpp
onnx_extended/ortcy/wrap/__init__.py
onnx_extended/ortcy/wrap/ortapi_inline.h
onnx_extended/ortcy/wrap/libonnxruntime.1.19.2.dylib
onnx_extended/ortcy/wrap/libonnxruntime.dylib
onnx_extended/ortcy/wrap/ortinf.cpython-311-darwin.so
onnx_extended/ortcy/wrap/ortapi.h
onnx_extended/ortcy/wrap/ortinf.pyx
onnx_extended/cpp/c_op_allocation.cpp
onnx_extended/cpp/onnx_extended_helpers.cpp
onnx_extended/cpp/__init__.py
onnx_extended/cpp/c_op_common_parameters.cpp
onnx_extended/cpp/cpu/__init__.py
