Metadata-Version: 2.2
Name: onnx-extended
Version: 0.4.0
Summary: Extends the list of supported operators in onnx reference implementation and onnxruntime, or implements faster versions in C++.
Home-page: https://github.com/sdpython/onnx-extended
Author: Xavier Dupré
Author-email: Xavier Dupré <xavier.dupre@gmail.com>
License: ﻿Copyright (c) 2023-2024, Xavier Dupré
Project-URL: Homepage, https://sdpython.github.io/doc/onnx-extended/dev/
Project-URL: Documentation, https://sdpython.github.io/doc/onnx-extended/dev/
Project-URL: Repository, https://github.com/sdpython/onnx-extended/
Project-URL: Changelog, https://github.com/sdpython/onnx-extended/blob/main/CHANGELOGS.rst
Project-URL: Issues, https://github.com/sdpython/onnx-extended/issues
Keywords: onnx,onnxruntime,CUDA,openmp,cmake,cython,pybind11
Classifier: Intended Audience :: Science/Research
Classifier: Intended Audience :: Developers
Classifier: License :: OSI Approved :: MIT License
Classifier: Programming Language :: C
Classifier: Programming Language :: Python
Classifier: Topic :: Software Development
Classifier: Topic :: Scientific/Engineering
Classifier: Development Status :: 5 - Production/Stable
Classifier: Operating System :: Microsoft :: Windows
Classifier: Operating System :: POSIX
Classifier: Operating System :: Unix
Classifier: Operating System :: MacOS
Classifier: Programming Language :: Python :: 3
Classifier: Programming Language :: Python :: 3.9
Classifier: Programming Language :: Python :: 3.10
Classifier: Programming Language :: Python :: 3.11
Classifier: Programming Language :: Python :: 3.12
Requires-Python: >=3.10
License-File: LICENSE.txt
Requires-Dist: numpy
Requires-Dist: onnx>=1.17.0
Requires-Dist: scipy
Provides-Extra: dev
Requires-Dist: autopep8; extra == "dev"
Requires-Dist: black; extra == "dev"
Requires-Dist: clang-format; extra == "dev"
Requires-Dist: cmakelang; extra == "dev"
Requires-Dist: coverage; extra == "dev"
Requires-Dist: cython; extra == "dev"
Requires-Dist: cython-lint; extra == "dev"
Requires-Dist: flake8; extra == "dev"
Requires-Dist: furo; extra == "dev"
Requires-Dist: isort; extra == "dev"
Requires-Dist: joblib; extra == "dev"
Requires-Dist: lightgbm; extra == "dev"
Requires-Dist: matplotlib; extra == "dev"
Requires-Dist: ml-dtypes; extra == "dev"
Requires-Dist: onnx-array-api; extra == "dev"
Requires-Dist: onnxmltools; extra == "dev"
Requires-Dist: onnxruntime; extra == "dev"
Requires-Dist: pandas; extra == "dev"
Requires-Dist: psutil; extra == "dev"
Requires-Dist: pytest; extra == "dev"
Requires-Dist: pytest-cov; extra == "dev"
Requires-Dist: ruff; extra == "dev"
Requires-Dist: scikit-learn; extra == "dev"
Requires-Dist: skl2onnx>=1.14.1; extra == "dev"
Requires-Dist: sphinx; extra == "dev"
Requires-Dist: sphinx-gallery; extra == "dev"
Requires-Dist: sphinx-issues; extra == "dev"
Requires-Dist: tqdm; extra == "dev"
Requires-Dist: wheel; extra == "dev"
Requires-Dist: xgboost; extra == "dev"
Dynamic: author
Dynamic: home-page
